dead_simple_self_learning/__init__.py
dead_simple_self_learning/__main__.py
dead_simple_self_learning/embedder.py
dead_simple_self_learning/learner.py
dead_simple_self_learning/memory.py
dead_simple_self_learning-1.1.4.dist-info/licenses/LICENSE
dead_simple_self_learning-1.1.4.dist-info/METADATA
dead_simple_self_learning-1.1.4.dist-info/WHEEL
dead_simple_self_learning-1.1.4.dist-info/top_level.txt
dead_simple_self_learning-1.1.4.dist-info/RECORD
