Metadata-Version: 2.4
Name: dead_simple_self_learning
Version: 1.1.4
Summary: A lightweight Python library that allows any LLM agent to self-improve through feedback, without retraining models.
Home-page: https://github.com/omdivyatej/Self-Learning-Agents
Author: Om Divyatej
Author-email: ohmbrock42@gmail.com
Project-URL: Bug Reports, https://github.com/omdivyatej/Self-Learning-Agents/issues
Project-URL: Source, https://github.com/omdivyatej/Self-Learning-Agents
Project-URL: Documentation, https://github.com/omdivyatej/Self-Learning-Agents#readme
Keywords: llm,embeddings,self-learning,agents,RAG,feedback,prompt-engineering,nlp
Classifier: Programming Language :: Python :: 3
Classifier: Programming Language :: Python :: 3.7
Classifier: Programming Language :: Python :: 3.8
Classifier: Programming Language :: Python :: 3.9
Classifier: Programming Language :: Python :: 3.10
Classifier: License :: OSI Approved :: MIT License
Classifier: Operating System :: OS Independent
Classifier: Intended Audience :: Developers
Classifier: Intended Audience :: Science/Research
Classifier: Topic :: Scientific/Engineering :: Artificial Intelligence
Classifier: Development Status :: 4 - Beta
Requires-Python: >=3.7
License-File: LICENSE
Requires-Dist: numpy>=1.20.0
Requires-Dist: openai>=1.0.0
Requires-Dist: transformers>=4.20.0
Requires-Dist: torch>=1.12.0
Requires-Dist: sentence-transformers>=2.2.0
Provides-Extra: openai
Requires-Dist: openai>=1.0.0; extra == "openai"
Provides-Extra: agno
Requires-Dist: agno>=0.1.0; extra == "agno"
Provides-Extra: langchain
Requires-Dist: langchain>=0.2.0; extra == "langchain"
Provides-Extra: dev
Requires-Dist: pytest>=7.0.0; extra == "dev"
Requires-Dist: black>=22.0.0; extra == "dev"
Requires-Dist: flake8>=5.0.0; extra == "dev"
Requires-Dist: mypy>=0.9.0; extra == "dev"
Provides-Extra: doc
Requires-Dist: sphinx>=4.0.0; extra == "doc"
Requires-Dist: sphinx-rtd-theme>=1.0.0; extra == "doc"
Dynamic: author
Dynamic: author-email
Dynamic: classifier
Dynamic: description
Dynamic: description-content-type
Dynamic: home-page
Dynamic: keywords
Dynamic: license-file
Dynamic: project-url
Dynamic: provides-extra
Dynamic: requires-dist
Dynamic: requires-python
Dynamic: summary
